[{"model": "services.service", "pk": 1, "fields": {"service_name": "Определение РНК вируса SARS CoV-2 методом ПЦР с типированием генетических вариантов, включая Омикрон (назофарингеальный мазок)", "description": "Приносим свои извинения, описание исследования находится в разработке.", "price": "2000.00"}}, {"model": "services.service", "pk": 2, "fields": {"service_name": "Гастроскопия", "description": "Эзофагогастродуоденоскопия\r\nЭндоскопический уреазный экспресс-тест на Helicobacter pylori\r\nЭзофагоскопия\r\nЭзофагогастродуоденоскопия трансназальная\r\nХромоскопия, контрастное исследовани", "price": "5000.00"}}, {"model": "services.service", "pk": 3, "fields": {"service_name": "Кардиограмма", "description": "Описание услуги 3", "price": "1000.00"}}]